Metadata-Version: 1.1
Name: oopwaiywaiy
Version: 0.0.2
Summary: OOP school learning by waiywaiy
Home-page: https://github.com/Waiywaiy/oopwaiywaiy
Author: Suppanimit meemungkit
Author-email: suppamee6@gmail.com
License: MIT
Download-URL: https://github.com/Waiywaiy/oopwaiywaiy/archive/refs/tags/v0.0.2.zip
Keywords: OOP example,School,oopwaiywaiy
Platform: UNKNOWN
Classifier: Development Status :: 3 - Alpha
Classifier: Intended Audience :: Education
Classifier: Topic :: Software Development :: Build Tools
Classifier: License :: OSI Approved :: MIT License
Classifier: Programming Language :: Python :: 3
Classifier: Programming Language :: Python :: 3.4
Classifier: Programming Language :: Python :: 3.5
Classifier: Programming Language :: Python :: 3.6
Classifier: Programming Language :: Python :: 3.7
Classifier: Programming Language :: Python :: 3.8
Classifier: Programming Language :: Python :: 3.9
